tempcatcher/__init__.py
tempcatcher/emails.txt
tempcatcher/tlds.txt
tempcatcher-1.0.0.dist-info/licenses/LICENSE
tempcatcher-1.0.0.dist-info/METADATA
tempcatcher-1.0.0.dist-info/WHEEL
tempcatcher-1.0.0.dist-info/top_level.txt
tempcatcher-1.0.0.dist-info/RECORD
