Metadata-Version: 2.4
Name: TempCatcher
Version: 1.0.0
Summary: Identify temporary email addresses using TempCatcher
Author-email: TempCatcher <contact@tempcatcher.com>
License-Expression: MIT
Project-URL: Homepage, https://github.com/TempCatcher/tempcatcher
Project-URL: Issues, https://github.com/TempCatcher/tempcatcher/issues
Classifier: Programming Language :: Python :: 3
Classifier: Operating System :: OS Independent
Requires-Python: >=3.9
License-File: LICENSE
Requires-Dist: dnspython>=2.7.0
Requires-Dist: requests>=2.32.5
Dynamic: license-file
